[
   {
      "type": "Улица",
      "street_name": "Добролюбова",
      "building_no": "9"
   },
   {
      "type": "Улица",
      "street_name": "Добролюбова",
      "building_no": "9а"
   },
   {
      "type": "Улица",
      "street_name": "Толмачева",
      "building_no": "8"
   },
   {
      "type": "Улица",
      "street_name": "Карла Либкнехта",
      "building_no": "9"
   },
   {
      "type": "Проспект",
      "street_name": "Ленина",
      "building_no": "69, корп. 2"
   },
   {
      "type": "Проспект",
      "street_name": "Ленина",
      "building_no": "69, корп. 3"
   },
   {
      "type": "Проспект",
      "street_name": "Ленина",
      "building_no": "69, корп. 4"
   },
   {
      "type": "Проспект",
      "street_name": "Ленина",
      "building_no": "69, корп. 5"
   },
   {
      "type": "Проспект",
      "street_name": "Ленина",
      "building_no": "69, корп. 6"
   },
   {
      "type": "Проспект",
      "street_name": "Ленина",
      "building_no": "69, корп. 7"
   },
   {
      "type": "Проспект",
      "street_name": "Ленина",
      "building_no": "69, корп. 8"
   },
   {
      "type": "Улица",
      "street_name": "Розы Люксембург",
      "building_no": "1"
   },
   {
      "type": "Улица",
      "street_name": "Розы Люксембург",
      "building_no": "1а"
   },
   {
      "type": "Улица",
      "street_name": "Вайнера",
      "building_no": "д. 64"
   },
   {
      "type": "Улица",
      "street_name": "Кирова",
      "building_no": "28"
   },
   {
      "type": "Улица",
      "street_name": "Толедова",
      "building_no": "43"
   },
   {
      "type": "Улица",
      "street_name": "Куйбышева",
      "building_no": "д. 48-А (корпус Г, литер А)"
   },
   {
      "type": "Улица",
      "street_name": "Куйбышева",
      "building_no": "д. 48-В (корпус А, литер В)"
   },
   {
      "type": "Проспект",
      "street_name": "Ленина",
      "building_no": "д. 29-б"
   },
   {
      "type": "Проспект",
      "street_name": "Ленина",
      "building_no": "29"
   },
   {
      "type": "Улица",
      "street_name": "Володарского",
      "building_no": "д. 2, литер Б"
   },
   {
      "type": "Проспект",
      "street_name": "Ленина",
      "building_no": "34"
   },
   {
      "type": "Улица",
      "street_name": "Пушкина",
      "building_no": "д. 11"
   },
   {
      "type": "Улица",
      "street_name": "Карла Маркса",
      "building_no": "4"
   },
   {
      "type": "Улица",
      "street_name": "Горького",
      "building": "32"
   },
   {
      "type": "Улица",
      "street_name": "Малышева",
      "building_no": "31-д"
   },
   {
      "type": "Улица",
      "street_name": "Воеводина",
      "building": "6"
   },
   {
      "type": "Улица",
      "street_name": "Розы Люксембург",
      "building_no": "50"
   },
   {
      "type": "Улица",
      "street_name": "Куйбышева",
      "building": "69"
   },
   {
      "type": "Улица",
      "street_name": "Стахановская",
      "building_no": "1"
   },
   {
      "type": "Проспект",
      "street_name": "Орджоникидзе",
      "building": "10"
   },
   {
      "type": "Улица",
      "street_name": "Челюскинцев",
      "building_no": "3"
   },
   {
      "type": "Переулок",
      "street_name": "Северный",
      "building": "2"
   },
   {
      "type": "Улица",
      "street_name": "Азина",
      "building_no": "22"
   },
   {
      "type": "Улица",
      "street_name": "Азина",
      "building_no": "22"
   },
   {
      "type": "Улица",
      "street_name": "Азина",
      "building_no": "22"
   },
   {
      "type": "Улица",
      "street_name": "Азина",
      "building_no": "22"
   },
   {
      "type": "Улица",
      "street_name": "Азина",
      "building_no": "22"
   },
   {
      "type": "Улица",
      "street_name": "Азина",
      "building_no": "27"
   },
   {
      "type": "Улица",
      "street_name": "Бажова",
      "building_no": "137"
   },
   {
      "type": "Улица",
      "street_name": "Бакинских комиссаров",
      "building_no": "2а"
   },
   {
      "type": "Переулок",
      "street_name": "Банковский",
      "building_no": "9"
   },
   {
      "type": "Улица",
      "street_name": "Баумана",
      "building_no": "2"
   },
   {
      "type": "Улица",
      "street_name": "Белинского",
      "building_no": "3"
   },
   {
      "type": "Улица",
      "street_name": "Белинского",
      "building_no": "6"
   },
   {
      "type": "Улица",
      "street_name": "Белинского",
      "building_no": "6"
   },
   {
      "type": "Улица",
      "street_name": "Белинского",
      "building_no": "6"
   },
   {
      "type": "Улица",
      "street_name": "Белинского",
      "building_no": "8-10"
   },
   {
      "type": "Улица",
      "street_name": "Белинского",
      "building_no": "11"
   },
   {
      "type": "Улица",
      "street_name": "Белинского",
      "building_no": "15"
   },
   {
      "type": "Улица",
      "street_name": "Белинского",
      "building_no": "19"
   },
   {
      "type": "Улица",
      "street_name": "Белинского",
      "building_no": "20"
   },
   {
      "type": "Улица",
      "street_name": "Белинского",
      "building_no": "59"
   },
   {
      "type": "Улица",
      "street_name": "Белинского",
      "building_no": "66"
   },
   {
      "type": "Улица",
      "street_name": "Бисертская",
      "building_no": "12а"
   },
   {
      "type": "Улица",
      "street_name": "Боевых дружин",
      "building_no": "26 / 15"
   },
   {
      "type": "Улица",
      "street_name": "Большакова",
      "building_no": "82"
   },
   {
      "type": "Улица",
      "street_name": "Большакова",
      "building_no": "84"
   },
   {
      "type": "Улица",
      "street_name": "Большакова",
      "building_no": "84"
   },
   {
      "type": "Улица",
      "street_name": "Большакова",
      "building_no": "86"
   },
   {
      "type": "Улица",
      "street_name": "Блюхера",
      "building_no": "5а"
   },
   {
      "type": "Улица",
      "street_name": "Братьев Быковых",
      "building_no": "11"
   },
   {
      "type": "Улица",
      "street_name": "Братьев Быковых",
      "building_no": "34а"
   },
   {
      "type": "Улица",
      "street_name": "Вайнера",
      "building_no": "1"
   },
   {
      "type": "Улица",
      "street_name": "Вайнера",
      "building_no": "3/5"
   },
   {
      "type": "Улица",
      "street_name": "Вайнера",
      "building_no": "9"
   },
   {
      "type": "Улица",
      "street_name": "Вайнера",
      "building_no": "9а"
   },
   {
      "type": "Улица",
      "street_name": "Вайнера",
      "building_no": "10"
   },
   {
      "type": "Улица",
      "street_name": "Вайнера",
      "building_no": "11"
   },
   {
      "type": "Улица",
      "street_name": "Вайнера",
      "building_no": "16"
   },
   {
      "type": "Улица",
      "street_name": "Вайнера",
      "building_no": "26"
   },
   {
      "type": "Улица",
      "street_name": "Вайнера",
      "building_no": "30"
   },
   {
      "type": "Улица",
      "street_name": "Вайнера",
      "building_no": "38"
   },
   {
      "type": "Улица",
      "street_name": "Вайнера",
      "building_no": "42"
   },
   {
      "type": "Улица",
      "street_name": "Вайнера",
      "building_no": "42"
   },
   {
      "type": "Улица",
      "street_name": "Вайнера",
      "building_no": "42"
   },
   {
      "type": "Улица",
      "street_name": "Вайнера",
      "building_no": "51"
   },
   {
      "type": "Улица",
      "street_name": "Вайнера",
      "building_no": "53"
   },
   {
      "type": "Улица",
      "street_name": "Вайнера",
      "building_no": "64 (левый)"
   },
   {
      "type": "Улица",
      "street_name": "Вайнера",
      "building_no": "64 (правый)"
   },
   {
      "type": "Улица",
      "street_name": "Венгерских коммунаров",
      "building_no": "56-а"
   },
   {
      "type": "Бульвар",
      "street_name": "Верх-Исетский",
      "building_no": "5"
   },
   {
      "type": "Бульвар",
      "street_name": "Верх-Исетский",
      "building_no": "15"
   },
   {
      "type": "Бульвар",
      "street_name": "Верх-Исетский",
      "building_no": "15"
   },
   {
      "type": "Бульвар",
      "street_name": "Верх-Исетский",
      "building_no": "15"
   },
   {
      "type": "Бульвар",
      "street_name": "Верх-Исетский",
      "building_no": "9"
   },
   {
      "type": "Бульвар",
      "street_name": "Верх-Исетский",
      "building_no": "18-20"
   },
   {
      "type": "Бульвар",
      "street_name": "Верх-Исетский",
      "building_no": "18"
   },
   {
      "type": "Бульвар",
      "street_name": "Верх-Исетский",
      "building_no": "20"
   },
   {
      "type": "Бульвар",
      "street_name": "Верх-Исетский",
      "building_no": "18"
   },
   {
      "type": "Бульвар",
      "street_name": "Верх-Исетский",
      "building_no": "20"
   },
   {
      "type": "Бульвар",
      "street_name": "Верх-Исетский",
      "building_no": "18-20"
   },
   {
      "type": "Бульвар",
      "street_name": "Верх-Исетский",
      "building_no": "18-20"
   },
   {
      "type": "Улица",
      "street_name": "Воеводина",
      "building_no": "5"
   },
   {
      "type": "Улица",
      "street_name": "Вокзальная",
      "building_no": "14"
   },
   {
      "type": "Улица",
      "street_name": "Вокзальная",
      "building_no": "14"
   },
   {
      "type": "Улица",
      "street_name": "Вокзальная",
      "building_no": "22"
   },
   {
      "type": "Улица",
      "street_name": "Володарского",
      "building_no": "9"
   },
   {
      "type": "Улица",
      "street_name": "8 Марта",
      "building_no": "1"
   },
   {
      "type": "Улица",
      "street_name": "8 Марта",
      "building_no": "2"
   },
   {
      "type": "Улица",
      "street_name": "8 Марта",
      "building_no": "3"
   },
   {
      "type": "Улица",
      "street_name": "8 Марта",
      "building_no": "5"
   },
   {
      "type": "Улица",
      "street_name": "8 Марта",
      "building_no": "8-б"
   },
   {
      "type": "Улица",
      "street_name": "8 Марта",
      "building_no": "8-д"
   },
   {
      "type": "Улица",
      "street_name": "8 Марта",
      "building_no": "12"
   },
   {
      "type": "Улица",
      "street_name": "8 Марта",
      "building_no": "16"
   },
   {
      "type": "Улица",
      "street_name": "8 Марта",
      "building_no": "16"
   },
   {
      "type": "Улица",
      "street_name": "8 Марта",
      "building_no": "18"
   },
   {
      "type": "Улица",
      "street_name": "8 Марта",
      "building_no": "19"
   },
   {
      "type": "Улица",
      "street_name": "8 Марта",
      "building_no": "19, литер Б"
   },
   {
      "type": "Улица",
      "street_name": "8 Марта",
      "building_no": "20"
   },
   {
      "type": "Улица",
      "street_name": "8 Марта",
      "building_no": "20"
   },
   {
      "type": "Улица",
      "street_name": "8 Марта",
      "building_no": "21"
   },
   {
      "type": "Улица",
      "street_name": "8 Марта",
      "building_no": "22"
   },
   {
      "type": "Улица",
      "street_name": "8 Марта",
      "building_no": "23"
   },
   {
      "type": "Улица",
      "street_name": "8 Марта",
      "building_no": "24"
   },
   {
      "type": "Улица",
      "street_name": "8 Марта",
      "building_no": "25"
   },
   {
      "type": "Улица",
      "street_name": "8 Марта",
      "building_no": "26"
   },
   {
      "type": "Улица",
      "street_name": "8 Марта",
      "building_no": "27"
   },
   {
      "type": "Улица",
      "street_name": "8 Марта",
      "building_no": "29"
   },
   {
      "type": "Улица",
      "street_name": "8 Марта",
      "building_no": "30"
   },
   {
      "type": "Улица",
      "street_name": "8 Марта",
      "building_no": "31"
   },
   {
      "type": "Улица",
      "street_name": "8 Марта",
      "building_no": "31, литер В"
   },
   {
      "type": "Улица",
      "street_name": "8 Марта",
      "building_no": "32"
   },
   {
      "type": "Улица",
      "street_name": "8 Марта",
      "building_no": "33"
   },
   {
      "type": "Улица",
      "street_name": "8 Марта",
      "building_no": "34"
   },
   {
      "type": "Улица",
      "street_name": "8 Марта",
      "building_no": "36"
   },
   {
      "type": "Улица",
      "street_name": "8 Марта",
      "building_no": "78а"
   },
   {
      "type": "Улица",
      "street_name": "8 Марта",
      "building_no": "202"
   },
   {
      "type": "Улица",
      "street_name": "Гастелло",
      "building_no": "42"
   },
   {
      "type": "Улица",
      "street_name": "Гоголя",
      "building_no": "7"
   },
   {
      "type": "Улица",
      "street_name": "Гоголя",
      "building_no": "20 / 5"
   },
   {
      "type": "Улица",
      "street_name": "Горького",
      "building_no": "6"
   },
   {
      "type": "Улица",
      "street_name": "Горького",
      "building_no": "7"
   },
   {
      "type": "Улица",
      "street_name": "Горького",
      "building_no": "8"
   },
   {
      "type": "Улица",
      "street_name": "Горького",
      "building_no": "14"
   },
   {
      "type": "Улица",
      "street_name": "Горького",
      "building_no": "21-23"
   },
   {
      "type": "Улица",
      "street_name": "Горького",
      "building_no": "28"
   },
   {
      "type": "Улица",
      "street_name": "Горького",
      "building_no": "33"
   },
   {
      "type": "Улица",
      "street_name": "Горького",
      "building_no": "34"
   },
   {
      "type": "Улица",
      "street_name": "Горького",
      "building_no": "39"
   },
   {
      "type": "Улица",
      "street_name": "Горького",
      "building_no": "41"
   },
   {
      "type": "Улица",
      "street_name": "Горького",
      "building_no": "43"
   },
   {
      "type": "Улица",
      "street_name": "Горького",
      "building_no": "45"
   },
   {
      "type": "Улица",
      "street_name": "Горького",
      "building_no": "49"
   },
   {
      "type": "Улица",
      "street_name": "Грибоедова",
      "building_no": "9"
   },
   {
      "type": "Улица",
      "street_name": "XXII партсъезда",
      "building_no": "6"
   },
   {
      "type": "Улица",
      "street_name": "Декабристов",
      "building_no": "32"
   },
   {
      "type": "Улица",
      "street_name": "Декабристов",
      "building_no": "32"
   },
   {
      "type": "Улица",
      "street_name": "Декабристов",
      "building_no": "32"
   },
   {
      "type": "Улица",
      "street_name": "Декабристов",
      "building_no": "32"
   },
   {
      "type": "Улица",
      "street_name": "Декабристов",
      "building_no": "32"
   },
   {
      "type": "Улица",
      "street_name": "Декабристов",
      "building_no": "32"
   },
   {
      "type": "Улица",
      "street_name": "Декабристов",
      "building_no": "34 / 66"
   },
   {
      "type": "Улица",
      "street_name": "Декабристов",
      "building_no": "36-38"
   },
   {
      "type": "Улица",
      "street_name": "Декабристов",
      "building_no": "36-38"
   },
   {
      "type": "Улица",
      "street_name": "Декабристов",
      "building_no": "36-38"
   },
   {
      "type": "Улица",
      "street_name": "Декабристов",
      "building_no": "36-38"
   },
   {
      "type": "Улица",
      "street_name": "Декабристов",
      "building_no": "40"
   },
   {
      "type": "Улица",
      "street_name": "Декабристов",
      "building_no": "40"
   },
   {
      "type": "Улица",
      "street_name": "Декабристов",
      "building_no": "40"
   },
   {
      "type": "Улица",
      "street_name": "Декабристов",
      "building_no": "40"
   },
   {
      "type": "Улица",
      "street_name": "Декабристов",
      "building_no": "41"
   },
   {
      "type": "Улица",
      "street_name": "Декабристов",
      "building_no": "56"
   },
   {
      "type": "Улица",
      "street_name": "Декабристов",
      "building_no": "58"
   },
   {
      "type": "Улица",
      "street_name": "Декабристов",
      "building_no": "83"
   },
   {
      "type": "Улица",
      "street_name": "Декабристов",
      "building_no": "87"
   },
   {
      "type": "Улица",
      "street_name": "Декабристов",
      "building_no": "87"
   },
   {
      "type": "Улица",
      "street_name": "Декабристов",
      "building_no": "87"
   },
   {
      "type": "Улица",
      "street_name": "Декабристов",
      "building_no": "87"
   },
   {
      "type": "Улица",
      "street_name": "Декабристов",
      "building_no": "87"
   },
   {
      "type": "Улица",
      "street_name": "Декабристов",
      "building_no": "87"
   },
   {
      "type": "Улица",
      "street_name": "Декабристов",
      "building_no": "87"
   },
   {
      "type": "Улица",
      "street_name": "Декабристов",
      "building_no": "87"
   },
   {
      "type": "Улица",
      "street_name": "Декабристов",
      "building_no": "87"
   },
   {
      "type": "Улица",
      "street_name": "Декабристов",
      "building_no": "87"
   },
   {
      "type": "Улица",
      "street_name": "Декабристов",
      "building_no": "87"
   },
   {
      "type": "Улица",
      "street_name": "Декабристов",
      "building_no": "87"
   },
   {
      "type": "Улица",
      "street_name": "Декабристов",
      "building_no": "87"
   },
   {
      "type": "Улица",
      "street_name": "Декабристов",
      "building_no": "87"
   },
   {
      "type": "Улица",
      "street_name": "Декабристов",
      "building_no": "87"
   },
   {
      "type": "Улица",
      "street_name": "Декабристов",
      "building_no": "87"
   },
   {
      "type": "Улица",
      "street_name": "Добролюбова",
      "building_no": "8"
   },
   {
      "type": "Улица",
      "street_name": "Добролюбова",
      "building_no": "10"
   },
   {
      "type": "Улица",
      "street_name": "Добролюбова",
      "building_no": "10"
   },
   {
      "type": "Улица",
      "street_name": "Добролюбова",
      "building_no": "10"
   },
   {
      "type": "Улица",
      "street_name": "Добролюбова",
      "building_no": "10"
   },
   {
      "type": "Улица",
      "street_name": "Добролюбова",
      "building_no": "12"
   },
   {
      "type": "Улица",
      "street_name": "Добролюбова",
      "building_no": "14"
   },
   {
      "type": "Улица",
      "street_name": "Добролюбова",
      "building_no": "19а"
   },
   {
      "type": "Улица",
      "street_name": "Д. Ибаррури",
      "building_no": "4"
   },
   {
      "type": "Улица",
      "street_name": "Д. Ибаррури",
      "building_no": "10-а"
   },
   {
      "type": "Улица",
      "street_name": "Еремина",
      "building_no": "12"
   },
   {
      "type": "Улица",
      "street_name": "Маршала Жукова",
      "building_no": "3"
   },
   {
      "type": "Улица",
      "street_name": "Каляева",
      "building_no": "34"
   },
   {
      "type": "Улица",
      "street_name": "Карла Либкнехта",
      "building_no": "2"
   },
   {
      "type": "Улица",
      "street_name": "Карла Либкнехта",
      "building_no": "3"
   },
   {
      "type": "Улица",
      "street_name": "Карла Либкнехта",
      "building_no": "5"
   },
   {
      "type": "Улица",
      "street_name": "Карла Либкнехта",
      "building_no": "8"
   },
   {
      "type": "Улица",
      "street_name": "Карла Либкнехта",
      "building_no": "8"
   },
   {
      "type": "Улица",
      "street_name": "Карла Либкнехта",
      "building_no": "8"
   },
   {
      "type": "Улица",
      "street_name": "Карла Либкнехта",
      "building_no": "8"
   },
   {
      "type": "Улица",
      "street_name": "Карла Либкнехта",
      "building_no": "8-б"
   },
   {
      "type": "Улица",
      "street_name": "Карла Либкнехта",
      "building_no": "9"
   },
   {
      "type": "Улица",
      "street_name": "Толмачева",
      "building_no": "8"
   },
   {
      "type": "Улица",
      "street_name": "Толмачева",
      "building_no": "8"
   },
   {
      "type": "Улица",
      "street_name": "Карла Либкнехта",
      "building_no": "9"
   },
   {
      "type": "Улица",
      "street_name": "Карла Либкнехта",
      "building_no": "25"
   },
   {
      "type": "Улица",
      "street_name": "Карла Либкнехта",
      "building_no": "26"
   },
   {
      "type": "Улица",
      "street_name": "Карла Либкнехта",
      "building_no": "32, литер А1"
   },
   {
      "type": "Улица",
      "street_name": "Карла Либкнехта",
      "building_no": "32"
   },
   {
      "type": "Улица",
      "street_name": "Карла Либкнехта",
      "building_no": "35"
   },
   {
      "type": "Улица",
      "street_name": "Карла Либкнехта",
      "building_no": "38"
   },
   {
      "type": "Улица",
      "street_name": "Карла Либкнехта",
      "building_no": "38а"
   },
   {
      "type": "Улица",
      "street_name": "Карла Либкнехта",
      "building_no": "39"
   },
   {
      "type": "Улица",
      "street_name": "Карла Либкнехта",
      "building_no": "42"
   },
   {
      "type": "Улица",
      "street_name": "Карла Либкнехта",
      "building_no": "44"
   },
   {
      "type": "Улица",
      "street_name": "Карла Либкнехта",
      "building_no": "45"
   },
   {
      "type": "Улица",
      "street_name": "Карла Либкнехта",
      "building_no": "45, литера А"
   },
   {
      "type": "Улица",
      "street_name": "Карла Маркса",
      "building_no": "2"
   },
   {
      "type": "Улица",
      "street_name": "Карла Маркса",
      "building_no": "8"
   },
   {
      "type": "Улица",
      "street_name": "Карла Маркса",
      "building_no": "8-а"
   },
   {
      "type": "Улица",
      "street_name": "Карла Маркса",
      "building_no": "20"
   },
   {
      "type": "Улица",
      "street_name": "Карла Маркса",
      "building_no": "22а"
   },
   {
      "type": "Улица",
      "street_name": "Карла Маркса",
      "building_no": "31"
   },
   {
      "type": "Улица",
      "street_name": "Кирова",
      "building_no": "1"
   },
   {
      "type": "Улица",
      "street_name": "Кирова",
      "building_no": "2"
   },
   {
      "type": "Улица",
      "street_name": "Кирова",
      "building_no": "3"
   },
   {
      "type": "Улица",
      "street_name": "Кирова",
      "building_no": "31"
   },
   {
      "type": "Улица",
      "street_name": "Кирова",
      "building_no": "32"
   },
   {
      "type": "Улица",
      "street_name": "Кирова",
      "building_no": "36"
   },
   {
      "type": "Улица",
      "street_name": "Кирова",
      "building_no": "49"
   },
   {
      "type": "Улица",
      "street_name": "Кирова",
      "building_no": "63"
   },
   {
      "type": "Улица",
      "street_name": "Кирова",
      "building_no": "65"
   },
   {
      "type": "Улица",
      "street_name": "Клары Цеткин",
      "building_no": "1"
   },
   {
      "type": "Улица",
      "street_name": "Клары Цеткин",
      "building_no": "13"
   },
   {
      "type": "Улица",
      "street_name": "Комсомольская",
      "building_no": "45, корп. 9"
   },
   {
      "type": "Улица",
      "street_name": "Косарева",
      "building_no": "1-а"
   },
   {
      "type": "Улица",
      "street_name": "Красноармейская",
      "building_no": "1"
   },
   {
      "type": "Улица",
      "street_name": "Красноармейская",
      "building_no": "8"
   },
   {
      "type": "Улица",
      "street_name": "Красноармейская",
      "building_no": "18"
   },
   {
      "type": "Улица",
      "street_name": "Красноармейская",
      "building_no": "28"
   },
   {
      "type": "Улица",
      "street_name": "Красноармейская",
      "building_no": "37б"
   },
   {
      "type": "Улица",
      "street_name": "Красноармейская",
      "building_no": "37б"
   },
   {
      "type": "Улица",
      "street_name": "Красноармейская",
      "building_no": "37б"
   },
   {
      "type": "Улица",
      "street_name": "Красноармейская",
      "building_no": "37б"
   },
   {
      "type": "Улица",
      "street_name": "Красноармейская",
      "building_no": "37в"
   },
   {
      "type": "Улица",
      "street_name": "Красноармейская",
      "building_no": "48"
   },
   {
      "type": "Улица",
      "street_name": "Красноармейская",
      "building_no": "70"
   },
   {
      "type": "Улица",
      "street_name": "Красноармейская",
      "building_no": "81"
   },
   {
      "type": "Улица",
      "street_name": "Красноармейская",
      "building_no": "89"
   },
   {
      "type": "Улица",
      "street_name": "Крылова",
      "building_no": "2"
   },
   {
      "type": "Улица",
      "street_name": "Куйбышева",
      "building_no": "24 / 127"
   },
   {
      "type": "Улица",
      "street_name": "Куйбышева",
      "building_no": "29"
   },
   {
      "type": "Улица",
      "street_name": "Куйбышева",
      "building_no": "30"
   },
   {
      "type": "Улица",
      "street_name": "Куйбышева",
      "building_no": "39"
   },
   {
      "type": "Улица",
      "street_name": "Куйбышева",
      "building_no": "40"
   },
   {
      "type": "Улица",
      "street_name": "Куйбышева",
      "building_no": "48"
   },
   {
      "type": "Улица",
      "street_name": "Куйбышева",
      "building_no": "48-Б (корпус Б, литер Б)"
   },
   {
      "type": "Улица",
      "street_name": "Куйбышева",
      "building_no": "63"
   },
   {
      "type": "Улица",
      "street_name": "Куйбышева",
      "building_no": "65"
   },
   {
      "type": "Улица",
      "street_name": "Куйбышева",
      "building_no": "99"
   },
   {
      "type": "Улица",
      "street_name": "Культуры",
      "building_no": "4"
   },
   {
      "type": "Улица",
      "street_name": "Культуры",
      "building_no": "6"
   },
   {
      "type": "Улица",
      "street_name": "Культуры",
      "building_no": "8"
   },
   {
      "type": "Проспект",
      "street_name": "Ленина",
      "building_no": "5"
   },
   {
      "type": "Проспект",
      "street_name": "Ленина",
      "building_no": "6"
   },
   {
      "type": "Проспект",
      "street_name": "Ленина",
      "building_no": "6"
   },
   {
      "type": "Проспект",
      "street_name": "Ленина",
      "building_no": "7"
   },
   {
      "type": "Проспект",
      "street_name": "Ленина",
      "building_no": "7"
   },
   {
      "type": "Проспект",
      "street_name": "Ленина",
      "building_no": "7"
   },
   {
      "type": "Улица",
      "street_name": "Шейнкмана",
      "building_no": "31"
   },
   {
      "type": "Проспект",
      "street_name": "Ленина",
      "building_no": "8"
   },
   {
      "type": "Проспект",
      "street_name": "Ленина",
      "building_no": "9"
   },
   {
      "type": "Проспект",
      "street_name": "Ленина",
      "building_no": "11"
   },
   {
      "type": "Проспект",
      "street_name": "Ленина",
      "building_no": "11"
   },
   {
      "type": "Проспект",
      "street_name": "Ленина",
      "building_no": "11"
   },
   {
      "type": "Улица",
      "street_name": "Сакко и Ванцетти",
      "building_no": "42"
   },
   {
      "type": "Проспект",
      "street_name": "Ленина",
      "building_no": "11"
   },
   {
      "type": "Проспект",
      "street_name": "Ленина",
      "building_no": "11"
   },
   {
      "type": "Проспект",
      "street_name": "Ленина",
      "building_no": "11"
   },
   {
      "type": "Улица",
      "street_name": "Сакко и Ванцетти",
      "building_no": "41"
   },
   {
      "type": "Улица",
      "street_name": "Сакко и Ванцетти",
      "building_no": "41"
   },
   {
      "type": "Проспект",
      "street_name": "Ленина",
      "building_no": "13-а"
   },
   {
      "type": "Проспект",
      "street_name": "Ленина",
      "building_no": "16"
   },
   {
      "type": "Проспект",
      "street_name": "Ленина",
      "building_no": "17"
   },
   {
      "type": "Проспект",
      "street_name": "Ленина",
      "building_no": "17а"
   },
   {
      "type": "Проспект",
      "street_name": "Ленина",
      "building_no": "18а"
   },
   {
      "type": "Проспект",
      "street_name": "Ленина",
      "building_no": "18"
   },
   {
      "type": "Проспект",
      "street_name": "Ленина",
      "building_no": "20"
   },
   {
      "type": "Проспект",
      "street_name": "Ленина",
      "building_no": "22"
   },
   {
      "type": "Улица",
      "street_name": "Хохрякова",
      "building_no": "1"
   },
   {
      "type": "Проспект",
      "street_name": "Ленина",
      "building_no": "22-а"
   },
   {
      "type": "Проспект",
      "street_name": "Ленина",
      "building_no": "24а"
   },
   {
      "type": "Проспект",
      "street_name": "Ленина",
      "building_no": "25"
   },
   {
      "type": "Улица",
      "street_name": "Вайнера",
      "building_no": "7"
   },
   {
      "type": "Проспект",
      "street_name": "Ленина",
      "building_no": "25"
   },
   {
      "type": "Проспект",
      "street_name": "Ленина",
      "building_no": "25"
   },
   {
      "type": "Проспект",
      "street_name": "Ленина",
      "building_no": "26"
   },
   {
      "type": "Проспект",
      "street_name": "Ленина",
      "building_no": "27"
   },
   {
      "type": "Проспект",
      "street_name": "Ленина",
      "building_no": "31"
   },
   {
      "type": "Улица",
      "street_name": "8 Марта",
      "building_no": "6"
   },
   {
      "type": "Улица",
      "street_name": "8 Марта",
      "building_no": "6"
   },
   {
      "type": "Проспект",
      "street_name": "Ленина",
      "building_no": "33"
   },
   {
      "type": "Проспект",
      "street_name": "Ленина",
      "building_no": "35"
   },
   {
      "type": "Проспект",
      "street_name": "Ленина",
      "building_no": "36"
   },
   {
      "type": "Проспект",
      "street_name": "Ленина",
      "building_no": "37"
   },
   {
      "type": "Проспект",
      "street_name": "Ленина",
      "building_no": "38"
   },
   {
      "type": "Проспект",
      "street_name": "Ленина",
      "building_no": "39"
   },
   {
      "type": "Проспект",
      "street_name": "Ленина",
      "building_no": "46"
   },
   {
      "type": "Проспект",
      "street_name": "Ленина",
      "building_no": "46а"
   },
   {
      "type": "Проспект",
      "street_name": "Ленина",
      "building_no": "49"
   },
   {
      "type": "Проспект",
      "street_name": "Ленина",
      "building_no": "50"
   },
   {
      "type": "Проспект",
      "street_name": "Ленина",
      "building_no": "51"
   },
   {
      "type": "Проспект",
      "street_name": "Ленина",
      "building_no": "52-54"
   },
   {
      "type": "Проспект",
      "street_name": "Ленина",
      "building_no": "58"
   },
   {
      "type": "Проспект",
      "street_name": "Ленина",
      "building_no": "60"
   },
   {
      "type": "Проспект",
      "street_name": "Ленина",
      "building_no": "69"
   },
   {
      "type": "Проспект",
      "street_name": "Ленина",
      "building_no": "69, корп. 13"
   },
   {
      "type": "Проспект",
      "street_name": "Ленина",
      "building_no": "69, корп. 14"
   },
   {
      "type": "Проспект",
      "street_name": "Ленина",
      "building_no": "69, корп. 1"
   },
   {
      "type": "Проспект",
      "street_name": "Ленина",
      "building_no": "69, корп. 10"
   },
   {
      "type": "Проспект",
      "street_name": "Ленина",
      "building_no": "69, корп. 12"
   },
   {
      "type": "Проспект",
      "street_name": "Ленина",
      "building_no": "69, корп. 10"
   },
   {
      "type": "Проспект",
      "street_name": "Ленина",
      "building_no": "69, корп. 10"
   },
   {
      "type": "Проспект",
      "street_name": "Ленина",
      "building_no": "71"
   },
   {
      "type": "Проспект",
      "street_name": "Ленина",
      "building_no": "71"
   },
   {
      "type": "Улица",
      "street_name": "Кузнечная",
      "building_no": "91"
   },
   {
      "type": "Улица",
      "street_name": "Первомайская",
      "building_no": "44"
   },
   {
      "type": "Улица",
      "street_name": "Кузнечная",
      "building_no": "91а"
   },
   {
      "type": "Проспект",
      "street_name": "Ленина",
      "building_no": "71"
   },
   {
      "type": "Проспект",
      "street_name": "Ленина",
      "building_no": "79"
   },
   {
      "type": "Проспект",
      "street_name": "Ленина",
      "building_no": "89"
   },
   {
      "type": "Проспект",
      "street_name": "Ленина",
      "building_no": "91"
   },
   {
      "type": "Проспект",
      "street_name": "Ленина",
      "building_no": "93"
   },
   {
      "type": "Проспект",
      "street_name": "Ленина",
      "building_no": "95"
   },
   {
      "type": "Проспект",
      "street_name": "Ленина",
      "building_no": "97"
   },
   {
      "type": "Проспект",
      "street_name": "Ленина",
      "building_no": "97а"
   },
   {
      "type": "Проспект",
      "street_name": "Ленина",
      "building_no": "99"
   },
   {
      "type": "Проспект",
      "street_name": "Ленина",
      "building_no": "101"
   },
   {
      "type": "Улица",
      "street_name": "Луначарского",
      "building_no": "173а"
   },
   {
      "type": "Улица",
      "street_name": "Луначарского",
      "building_no": "177"
   },
   {
      "type": "Улица",
      "street_name": "Луначарского",
      "building_no": "215"
   },
   {
      "type": "Улица",
      "street_name": "Малышева",
      "building_no": "2б"
   },
   {
      "type": "Улица",
      "street_name": "Малышева",
      "building_no": "2ж"
   },
   {
      "type": "Улица",
      "street_name": "Малышева",
      "building_no": "2е"
   },
   {
      "type": "Улица",
      "street_name": "Малышева",
      "building_no": "23"
   },
   {
      "type": "Улица",
      "street_name": "Малышева",
      "building_no": "29-а"
   },
   {
      "type": "Улица",
      "street_name": "Малышева",
      "building_no": "31-в"
   },
   {
      "type": "Улица",
      "street_name": "Малышева",
      "building_no": "35"
   },
   {
      "type": "Улица",
      "street_name": "Малышева",
      "building_no": "42"
   },
   {
      "type": "Улица",
      "street_name": "Малышева",
      "building_no": "46"
   },
   {
      "type": "Улица",
      "street_name": "Малышева",
      "building_no": "46"
   },
   {
      "type": "Улица",
      "street_name": "Малышева",
      "building_no": "56"
   },
   {
      "type": "Улица",
      "street_name": "Малышева",
      "building_no": "58/37"
   },
   {
      "type": "Улица",
      "street_name": "Малышева",
      "building_no": "58а"
   },
   {
      "type": "Улица",
      "street_name": "Малышева",
      "building_no": "68"
   },
   {
      "type": "Улица",
      "street_name": "Малышева",
      "building_no": "74"
   },
   {
      "type": "Улица",
      "street_name": "Малышева",
      "building_no": "76"
   },
   {
      "type": "Улица",
      "street_name": "Мамина-Сибиряка",
      "building_no": "99"
   },
   {
      "type": "Улица",
      "street_name": "Мамина-Сибиряка",
      "building_no": "114"
   },
   {
      "type": "Улица",
      "street_name": "Мамина-Сибиряка",
      "building_no": "145"
   },
   {
      "type": "Улица",
      "street_name": "Мамина-Сибиряка",
      "building_no": "187"
   },
   {
      "type": "Улица",
      "street_name": "Мира",
      "building_no": "17"
   },
   {
      "type": "Улица",
      "street_name": "Мира",
      "building_no": "19"
   },
   {
      "type": "Улица",
      "street_name": "Мира",
      "building_no": "21"
   },
   {
      "type": "Улица",
      "street_name": "Мира",
      "building_no": "28"
   },
   {
      "type": "Улица",
      "street_name": "Московская",
      "building_no": "12"
   },
   {
      "type": "Улица",
      "street_name": "Репина",
      "building_no": "2"
   },
   {
      "type": "Улица",
      "street_name": "Московская",
      "building_no": "14"
   },
   {
      "type": "Улица",
      "street_name": "Московская",
      "building_no": "19"
   },
   {
      "type": "Улица",
      "street_name": "Московская",
      "building_no": "28-б"
   },
   {
      "type": "Улица",
      "street_name": "Нагорная",
      "building_no": "50"
   },
   {
      "type": "Улица",
      "street_name": "Народной Воли",
      "building_no": "64"
   },
   {
      "type": "Улица",
      "street_name": "Октябрьской революции",
      "building_no": "35"
   },
   {
      "type": "Улица",
      "street_name": "Октябрьской революции",
      "building_no": "33а"
   },
   {
      "type": "Улица",
      "street_name": "Октябрьской революции",
      "building_no": "40"
   },
   {
      "type": "Улица",
      "street_name": "Октябрьской революции",
      "building_no": "52"
   },
   {
      "type": "Улица",
      "street_name": "Отдыха",
      "building_no": "55"
   },
   {
      "type": "Улица",
      "street_name": "Первомайская",
      "building_no": "7"
   },
   {
      "type": "Улица",
      "street_name": "Первомайская",
      "building_no": "11"
   },
   {
      "type": "Улица",
      "street_name": "Первомайская",
      "building_no": "13/16"
   },
   {
      "type": "Улица",
      "street_name": "Первомайская",
      "building_no": "22"
   },
   {
      "type": "Улица",
      "street_name": "Первомайская",
      "building_no": "24"
   },
   {
      "type": "Улица",
      "street_name": "Первомайская",
      "building_no": "27"
   },
   {
      "type": "Улица",
      "street_name": "Первомайская",
      "building_no": "43"
   },
   {
      "type": "Улица",
      "street_name": "Первомайская",
      "building_no": "71"
   },
   {
      "type": "Улица",
      "street_name": "Попова",
      "building_no": "4"
   },
   {
      "type": "Улица",
      "street_name": "Попова",
      "building_no": "11"
   },
   {
      "type": "Улица",
      "street_name": "Походная",
      "building_no": "2"
   },
   {
      "type": "Улица",
      "street_name": "Пролетарская",
      "building_no": "3"
   },
   {
      "type": "Улица",
      "street_name": "Пролетарская",
      "building_no": "6"
   },
   {
      "type": "Улица",
      "street_name": "Пролетарская",
      "building_no": "9"
   },
   {
      "type": "Улица",
      "street_name": "Пролетарская",
      "building_no": "10"
   },
   {
      "type": "Улица",
      "street_name": "Пушкина",
      "building_no": "4"
   },
   {
      "type": "Улица",
      "street_name": "Пушкина",
      "building_no": "5"
   },
   {
      "type": "Улица",
      "street_name": "Пушкина",
      "building_no": "7"
   },
   {
      "type": "Улица",
      "street_name": "Пушкина",
      "building_no": "8"
   },
   {
      "type": "Улица",
      "street_name": "Пушкина",
      "building_no": "12"
   },
   {
      "type": "Улица",
      "street_name": "Пушкина",
      "building_no": "14"
   },
   {
      "type": "Улица",
      "street_name": "Пушкина",
      "building_no": "16"
   },
   {
      "type": "Улица",
      "street_name": "Пушкина",
      "building_no": "19"
   },
   {
      "type": "Улица",
      "street_name": "Пушкина",
      "building_no": "27"
   },
   {
      "type": "Улица",
      "street_name": "Радищева",
      "building_no": "6-8"
   },
   {
      "type": "Улица",
      "street_name": "Радищева",
      "building_no": "6"
   },
   {
      "type": "Улица",
      "street_name": "Радищева",
      "building_no": "6-8"
   },
   {
      "type": "Улица",
      "street_name": "Радищева",
      "building_no": "8"
   },
   {
      "type": "Улица",
      "street_name": "Радищева",
      "building_no": "8"
   },
   {
      "type": "Улица",
      "street_name": "Радищева",
      "building_no": "16"
   },
   {
      "type": "Улица",
      "street_name": "Радищева",
      "building_no": "27"
   },
   {
      "type": "Улица",
      "street_name": "Репина",
      "building_no": "1"
   },
   {
      "type": "Улица",
      "street_name": "Репина",
      "building_no": "3"
   },
   {
      "type": "Улица",
      "street_name": "Репина",
      "building_no": "5"
   },
   {
      "type": "Улица",
      "street_name": "Репина",
      "building_no": "6"
   },
   {
      "type": "Улица",
      "street_name": "Розы Люксембург",
      "building_no": "1-а"
   },
   {
      "type": "Улица",
      "street_name": "Розы Люксембург",
      "building_no": "3"
   },
   {
      "type": "Улица",
      "street_name": "Розы Люксембург",
      "building_no": "5"
   },
   {
      "type": "Улица",
      "street_name": "Розы Люксембург",
      "building_no": "7"
   },
   {
      "type": "Улица",
      "street_name": "Розы Люксембург",
      "building_no": "8-10, литер А"
   },
   {
      "type": "Улица",
      "street_name": "Розы Люксембург",
      "building_no": "9"
   },
   {
      "type": "Улица",
      "street_name": "Розы Люксембург",
      "building_no": "10"
   },
   {
      "type": "Улица",
      "street_name": "Розы Люксембург",
      "building_no": "14"
   },
   {
      "type": "Улица",
      "street_name": "Розы Люксембург",
      "building_no": "14а"
   },
   {
      "type": "Улица",
      "street_name": "Розы Люксембург",
      "building_no": "15"
   },
   {
      "type": "Улица",
      "street_name": "Розы Люксембург",
      "building_no": "16"
   },
   {
      "type": "Улица",
      "street_name": "Розы Люксембург",
      "building_no": "18"
   },
   {
      "type": "Улица",
      "street_name": "Розы Люксембург",
      "building_no": "19"
   },
   {
      "type": "Улица",
      "street_name": "Розы Люксембург",
      "building_no": "20"
   },
   {
      "type": "Улица",
      "street_name": "Розы Люксембург",
      "building_no": "26"
   },
   {
      "type": "Улица",
      "street_name": "Розы Люксембург",
      "building_no": "27"
   },
   {
      "type": "Улица",
      "street_name": "Розы Люксембург",
      "building_no": "30"
   },
   {
      "type": "Улица",
      "street_name": "Розы Люксембург",
      "building_no": "34"
   },
   {
      "type": "Улица",
      "street_name": "Розы Люксембург",
      "building_no": "36"
   },
   {
      "type": "Улица",
      "street_name": "Розы Люксембург",
      "building_no": "38/13"
   },
   {
      "type": "Улица",
      "street_name": "Розы Люксембург",
      "building_no": "43"
   },
   {
      "type": "Улица",
      "street_name": "Розы Люксембург",
      "building_no": "45"
   },
   {
      "type": "Улица",
      "street_name": "Розы Люксембург",
      "building_no": "51"
   },
   {
      "type": "Улица",
      "street_name": "Розы Люксембург",
      "building_no": "53"
   },
   {
      "type": "Улица",
      "street_name": "Розы Люксембург",
      "building_no": "54"
   },
   {
      "type": "Улица",
      "street_name": "Розы Люксембург",
      "building_no": "56"
   },
   {
      "type": "Улица",
      "street_name": "Розы Люксембург",
      "building_no": "57"
   },
   {
      "type": "Улица",
      "street_name": "Розы Люксембург",
      "building_no": "60"
   },
   {
      "type": "Улица",
      "street_name": "Розы Люксембург",
      "building_no": "62"
   },
   {
      "type": "Улица",
      "street_name": "Розы Люксембург",
      "building_no": "62"
   },
   {
      "type": "Улица",
      "street_name": "Розы Люксембург",
      "building_no": "62"
   },
   {
      "type": "Улица",
      "street_name": "Розы Люксембург",
      "building_no": "62"
   },
   {
      "type": "Улица",
      "street_name": "Розы Люксембург",
      "building_no": "63"
   },
   {
      "type": "Улица",
      "street_name": "Розы Люксембург",
      "building_no": "65-67"
   },
   {
      "type": "Улица",
      "street_name": "Розы Люксембург",
      "building_no": "65"
   },
   {
      "type": "Улица",
      "street_name": "Розы Люксембург",
      "building_no": "67"
   },
   {
      "type": "Улица",
      "street_name": "Розы Люксембург",
      "building_no": "65-67"
   },
   {
      "type": "Улица",
      "street_name": "Розы Люксембург",
      "building_no": "73"
   },
   {
      "type": "Улица",
      "street_name": "Розы Люксембург",
      "building_no": "75"
   },
   {
      "type": "Улица",
      "street_name": "Сакко и Ванцетти",
      "building_no": "23"
   },
   {
      "type": "Улица",
      "street_name": "Сакко и Ванцетти",
      "building_no": "24"
   },
   {
      "type": "Улица",
      "street_name": "Сакко и Ванцетти",
      "building_no": "25"
   },
   {
      "type": "Улица",
      "street_name": "Сакко и Ванцетти",
      "building_no": "28"
   },
   {
      "type": "Улица",
      "street_name": "Сакко и Ванцетти",
      "building_no": "45"
   },
   {
      "type": "Улица",
      "street_name": "Сакко и Ванцетти",
      "building_no": "52"
   },
   {
      "type": "Улица",
      "street_name": "Сакко и Ванцетти",
      "building_no": "58а"
   },
   {
      "type": "Улица",
      "street_name": "Сакко и Ванцетти",
      "building_no": "69"
   },
   {
      "type": "Улица",
      "street_name": "Сакко и Ванцетти",
      "building_no": "115"
   },
   {
      "type": "Улица",
      "street_name": "Свердлова",
      "building_no": "8"
   },
   {
      "type": "Улица",
      "street_name": "Свердлова",
      "building_no": "11а"
   },
   {
      "type": "Улица",
      "street_name": "Свердлова",
      "building_no": "11"
   },
   {
      "type": "Улица",
      "street_name": "Свердлова",
      "building_no": "15"
   },
   {
      "type": "Улица",
      "street_name": "Свердлова",
      "building_no": "22"
   },
   {
      "type": "Улица",
      "street_name": "Свердлова",
      "building_no": "25"
   },
   {
      "type": "Улица",
      "street_name": "Свердлова",
      "building_no": "27"
   },
   {
      "type": "Улица",
      "street_name": "Свердлова",
      "building_no": "30"
   },
   {
      "type": "Улица",
      "street_name": "Свердлова",
      "building_no": "34"
   },
   {
      "type": "Улица",
      "street_name": "Свердлова",
      "building_no": "56"
   },
   {
      "type": "Улица",
      "street_name": "Свердлова",
      "building_no": "58"
   },
   {
      "type": "Улица",
      "street_name": "Свердлова",
      "building_no": "60"
   },
   {
      "type": "Улица",
      "street_name": "Свердлова",
      "building_no": "62"
   },
   {
      "type": "Улица",
      "street_name": "Свердлова",
      "building_no": "66"
   },
   {
      "type": "Тракт",
      "street_name": "Сибирский",
      "building_no": "19"
   },
   {
      "type": "Тракт",
      "street_name": "Сибирский",
      "building_no": "37"
   },
   {
      "type": "Тракт",
      "street_name": "Сибирский",
      "building_no": "14 км"
   },
   {
      "type": "Улица",
      "street_name": "Синяева",
      "building_no": "40"
   },
   {
      "type": "Улица",
      "street_name": "Синяева",
      "building_no": "60"
   },
   {
      "type": "Улица",
      "street_name": "Сони Морозовой",
      "building_no": "192"
   },
   {
      "type": "Улица",
      "street_name": "Софьи Ковалевской",
      "building_no": "18"
   },
   {
      "type": "Улица",
      "street_name": "Софьи Ковалевской",
      "building_no": "20"
   },
   {
      "type": "Улица",
      "street_name": "Старых большевиков",
      "building_no": "9"
   },
   {
      "type": "Улица",
      "street_name": "Старых большевиков",
      "building_no": "22"
   },
   {
      "type": "Улица",
      "street_name": "Синяева",
      "building_no": "58"
   },
   {
      "type": "Улица",
      "street_name": "Тверитина",
      "building_no": "54/77"
   },
   {
      "type": "Переулок",
      "street_name": "Театральный",
      "building_no": "5/4"
   },
   {
      "type": "Переулок",
      "street_name": "Театральный",
      "building_no": "7/9"
   },
   {
      "type": "Улица",
      "street_name": "Толмачева",
      "building_no": "7"
   },
   {
      "type": "Улица",
      "street_name": "Толмачева",
      "building_no": "11"
   },
   {
      "type": "Улица",
      "street_name": "Толмачева",
      "building_no": "21"
   },
   {
      "type": "Улица",
      "street_name": "Толмачева",
      "building_no": "24"
   },
   {
      "type": "Улица",
      "street_name": "Толмачева",
      "building_no": "41"
   },
   {
      "type": "Улица",
      "street_name": "Тургенева",
      "building_no": "15"
   },
   {
      "type": "Улица",
      "street_name": "Тургенева",
      "building_no": "18"
   },
   {
      "type": "Улица",
      "street_name": "Тургенева",
      "building_no": "20"
   },
   {
      "type": "Улица",
      "street_name": "Тургенева",
      "building_no": "22"
   },
   {
      "type": "Улица",
      "street_name": "Тургенева",
      "building_no": "24"
   },
   {
      "type": "Улица",
      "street_name": "Тургенева",
      "building_no": "28"
   },
   {
      "type": "Переулок",
      "street_name": "Университетский",
      "building_no": "9"
   },
   {
      "type": "Улица",
      "street_name": "Ильича",
      "building_no": "2"
   },
   {
      "type": "Улица",
      "street_name": "Февральской революции",
      "building_no": "9"
   },
   {
      "type": "Улица",
      "street_name": "Февральской революции",
      "building_no": "11"
   },
   {
      "type": "Улица",
      "street_name": "Февральской революции",
      "building_no": "27"
   },
   {
      "type": "Улица",
      "street_name": "Февральской революции",
      "building_no": "27"
   },
   {
      "type": "Улица",
      "street_name": "Февральской революции",
      "building_no": "37"
   },
   {
      "type": "Улица",
      "street_name": "Февральской революции",
      "building_no": "51"
   },
   {
      "type": "Улица",
      "street_name": "Физкультурников",
      "building_no": "30"
   },
   {
      "type": "Улица",
      "street_name": "Фронтовых бригад",
      "building_no": "18"
   },
   {
      "type": "Улица",
      "street_name": "Хохрякова",
      "building_no": "3"
   },
   {
      "type": "Улица",
      "street_name": "Хохрякова",
      "building_no": "5"
   },
   {
      "type": "Улица",
      "street_name": "Хохрякова",
      "building_no": "6"
   },
   {
      "type": "Улица",
      "street_name": "Хохрякова",
      "building_no": "9"
   },
   {
      "type": "Улица",
      "street_name": "Хохрякова",
      "building_no": "24"
   },
   {
      "type": "Улица",
      "street_name": "Хохрякова",
      "building_no": "27"
   },
   {
      "type": "Улица",
      "street_name": "Хохрякова",
      "building_no": "29"
   },
   {
      "type": "Улица",
      "street_name": "Хохрякова",
      "building_no": "31"
   },
   {
      "type": "Улица",
      "street_name": "Хохрякова",
      "building_no": "33"
   },
   {
      "type": "Улица",
      "street_name": "Хохрякова",
      "building_no": "42а"
   },
   {
      "type": "Улица",
      "street_name": "Хохрякова",
      "building_no": "62"
   },
   {
      "type": "Улица",
      "street_name": "Хохрякова",
      "building_no": "64"
   },
   {
      "type": "Улица",
      "street_name": "Хохрякова",
      "building_no": "68"
   },
   {
      "type": "Улица",
      "street_name": "Хохрякова",
      "building_no": "72"
   },
   {
      "type": "Улица",
      "street_name": "Горького",
      "building_no": "4а"
   },
   {
      "type": "Улица",
      "street_name": "Горького",
      "building_no": "4а"
   },
   {
      "type": "Улица",
      "street_name": "Горького",
      "building_no": "4"
   },
   {
      "type": "Улица",
      "street_name": "Горького",
      "building_no": "4а"
   },
   {
      "type": "Улица",
      "street_name": "Горького",
      "building_no": "4а"
   },
   {
      "type": "Улица",
      "street_name": "Чапаева",
      "building_no": "1"
   },
   {
      "type": "Улица",
      "street_name": "Чапаева",
      "building_no": "2"
   },
   {
      "type": "Улица",
      "street_name": "Чапаева",
      "building_no": "3"
   },
   {
      "type": "Улица",
      "street_name": "Чапаева",
      "building_no": "5"
   },
   {
      "type": "Улица",
      "street_name": "Чапаева",
      "building_no": "7"
   },
   {
      "type": "Улица",
      "street_name": "Чапаева",
      "building_no": "8"
   },
   {
      "type": "Улица",
      "street_name": "Чапаева",
      "building_no": "10"
   },
   {
      "type": "Улица",
      "street_name": "Чапаева",
      "building_no": "10"
   },
   {
      "type": "Улица",
      "street_name": "Чапаева",
      "building_no": "14"
   },
   {
      "type": "Улица",
      "street_name": "Челюскинцев",
      "building_no": "11"
   },
   {
      "type": "Улица",
      "street_name": "Челюскинцев",
      "building_no": "58"
   },
   {
      "type": "Улица",
      "street_name": "Челюскинцев",
      "building_no": "100"
   },
   {
      "type": "Улица",
      "street_name": "Челюскинцев",
      "building_no": "102"
   },
   {
      "type": "Улица",
      "street_name": "Чернышевского",
      "building_no": "2"
   },
   {
      "type": "Улица",
      "street_name": "Чернышевского",
      "building_no": "9"
   },
   {
      "type": "Улица",
      "street_name": "Шарташская",
      "building_no": "13"
   },
   {
      "type": "Улица",
      "street_name": "Шейнкмана",
      "building_no": "18"
   },
   {
      "type": "Улица",
      "street_name": "Шейнкмана",
      "building_no": "31"
   },
   {
      "type": "Улица",
      "street_name": "Шейнкмана",
      "building_no": "42"
   },
   {
      "type": "Улица",
      "street_name": "Шейнкмана",
      "building_no": "83"
   },
   {
      "type": "Улица",
      "street_name": "Школьников",
      "building_no": "1"
   },
   {
      "type": "Улица",
      "street_name": "Щедрина",
      "building_no": "10"
   },
   {
      "type": "Улица",
      "street_name": "Щедрина",
      "building_no": "18-а"
   },
   {
      "type": "Улица",
      "street_name": "Щербакова",
      "building_no": "67"
   },
   {
      "type": "Улица",
      "street_name": "Энгельса",
      "building_no": "6"
   }
]